<dest_subchaser_anim_winter_2_no_aa.xml>
  <parent>default.xml</parent>
  <name>BOATS</name>
  <bBoxes>
    <mainBox>
      <size>100 90 100</size>
    </mainBox>
  </bBoxes>
  <damageEffects>
    <effectFire>EFFECT_fire_med_01</effectFire>
    <destroy>EFFECT_w_part_exposion_small</destroy>
  </damageEffects>
  <maxHealth>	1200	</maxHealth>
  <dominationCost>0.08</dominationCost>
  <respawnDelay>-1.0</respawnDelay>
  <superiorityPoints>	0	</superiorityPoints>
  <superiorityPointsGroup1>	0	</superiorityPointsGroup1>
  <superiorityPointsGroup2>	6	</superiorityPointsGroup2>
  <superiorityPointsGroup3>	1	</superiorityPointsGroup3>
  <superiorityPointsGroup4>	6	</superiorityPointsGroup4>
  <superiorityPointsGroup5>	1	</superiorityPointsGroup5>
  <superiorityPointsGroup6>	0	</superiorityPointsGroup6>
  <initialSpawnDelay>0.0</initialSpawnDelay>
  <type>vehicle</type>
  <parts>
    <part>
      <name>	hull	</name>
      <partId>	1	</partId>
      <groupId>	1	</groupId>
      <mountPoint>
      </mountPoint>
      <upgrade>
        <id>	1	</id>
        <bBoxes>
        </bBoxes>
        <health>	0	</health>
        <componentType>	Hull	</componentType>
        <componentXml>server.todo.xml</componentXml>
        <states>
          <state>
            <id>	1	</id>
            <stateAction>	0	</stateAction>
            <usage>
            </usage>
            <stateHelthCfc>1.00000</stateHelthCfc>
            <model>content/Test_for_GD/typical_objects/big_layout_1.model</model>
            <subItems>
            </subItems>
            <animationController>
            </animationController>
            <stateFireChance>	0.200000	</stateFireChance>
            <fallingOutModel>
            </fallingOutModel>
            <stateAnimation>
            </stateAnimation>
          </state>
        </states>
        <repairDestructedAfter>	-1.000000	</repairDestructedAfter>
        <fireMountPoint>
        </fireMountPoint>
        <componentTypeQuota>	1.000000	</componentTypeQuota>
        <componentPosition>Front</componentPosition>
      </upgrade>
    </part>
    <part>
      <name>ship1</name>
      <partId>	2	</partId>
      <groupId>	2	</groupId>
      <mountPoint>hull/HP_sp_3</mountPoint>
      <upgrade>
        <id>	1	</id>
        <bBoxes>
          <bbox>
            <position>	-15.435000 0.540000 -9.405000	</position>
            <size>	6.660000 4.050000 34.740000	</size>
            <armorFront>	0.000000 0.000000 0.000000	</armorFront>
            <armorBack>	0.000000 0.000000 0.000000	</armorBack>
            <absorption>	0.200000	</absorption>
            <rotation>	0.000000 0.000000 0.000000 1.000000	</rotation>
          </bbox>
        </bBoxes>
        <health>	450	</health>
        <componentType>Collidable</componentType>
        <componentXml>server.todo.xml</componentXml>
        <states>
          <state>
            <id>	1	</id>
            <usage>
            </usage>
            <stateAction>	0	</stateAction>
            <stateHelthCfc>	1.000000	</stateHelthCfc>
            <model>content/dest/ship/US/Subchaser_destructible/Winter/mech_CV_Subchaser.model</model>
            <effectState>
              <effect>
                <name>EFFECT_static_ship_39</name>
                <mountPoint>HP_stream</mountPoint>
              </effect>
            </effectState>
            <stateAnimation>
            </stateAnimation>
            <subItems>
            </subItems>
            <animationController>
            </animationController>
            <stateFireChance>	0.200000	</stateFireChance>
            <fallingOutModel>
            </fallingOutModel>
          </state>
          <state>
            <id>	2	</id>
            <usage>
            </usage>
            <stateAction>	0	</stateAction>
            <stateHelthCfc>	0.800000	</stateHelthCfc>
            <model>content/dest/ship/US/Subchaser_destructible/Winter/mech_CV_Subchaser.model</model>
            <effectState>
              <effect>
                <name>EFFECT_static_ship_39</name>
                <mountPoint>HP_stream</mountPoint>
              </effect>
            </effectState>
            <stateAnimation>
            </stateAnimation>
            <subItems>
            </subItems>
            <animationController>
            </animationController>
            <stateFireChance>	0.200000	</stateFireChance>
            <fallingOutModel>
            </fallingOutModel>
          </state>
          <state>
            <id>	3	</id>
            <usage>
            </usage>
            <stateAction>	0	</stateAction>
            <stateHelthCfc>	0.300000	</stateHelthCfc>
            <model>content/dest/ship/US/Subchaser_destructible/Winter/mech_CV_Subchaser.model</model>
            <effectState>
              <effect>
                <name>EFFECT_static_ship_39</name>
                <mountPoint>HP_stream</mountPoint>
              </effect>
            </effectState>
            <stateAnimation>
            </stateAnimation>
            <subItems>
            </subItems>
            <animationController>
            </animationController>
            <stateFireChance>	0.200000	</stateFireChance>
            <fallingOutModel>
            </fallingOutModel>
          </state>
          <state>
            <id>	4	</id>
            <bBoxes>
              <bbox>
                <position>	-15.435000 0.540000 -9.405000	</position>
                <size>4.662 2.835 24.3179986</size>
                <armorFront>0.0 0.0 0.0</armorFront>
                <armorBack>0.0 0.0 0.0</armorBack>
                <absorption>	1.000000	</absorption>
                <rotation>	0.000000 0.000000 0.000000 1.000000	</rotation>
              </bbox>
            </bBoxes>
            <usage>crash</usage>
            <stateAction>	0	</stateAction>
            <stateHelthCfc>	0.000000	</stateHelthCfc>
            <model>content/dest/ship/US/Subchaser_destructible/Winter/mech_CV_Subchaser_crash.model</model>
            <effectState>
            </effectState>
            <effectOnStart>
              <effect>
                <name>EFFECT_w_part_exposion_small</name>
                <mountPoint>HP_explosion_part1</mountPoint>
              </effect>
              <effect>
                <name>EFFECT_w_part_exposion_small</name>
                <mountPoint>HP_explosion_gun_nose</mountPoint>
              </effect>
              <effect>
                <name>EFFECT_w_part_exposion_small</name>
                <mountPoint>HP_explosion_gun_end</mountPoint>
              </effect>
            </effectOnStart>
            <stateAnimation>death,idle</stateAnimation>
            <affectedParts>
              <part>
                <partID>	3	</partID>
                <minimalPartState>	5	</minimalPartState>
              </part>
              <part>
                <partID>	4	</partID>
                <minimalPartState>	3	</minimalPartState>
              </part>
              <part>
                <partID>	6	</partID>
                <minimalPartState>	3	</minimalPartState>
              </part>
              <part>
                <partID>	7	</partID>
                <minimalPartState>	3	</minimalPartState>
              </part>
              <part>
                <partID>	8	</partID>
                <minimalPartState>	3	</minimalPartState>
              </part>
              <part>
                <partID>	9	</partID>
                <minimalPartState>	3	</minimalPartState>
              </part>
            </affectedParts>
            <subItems>
            </subItems>
            <animationController>
            </animationController>
            <stateFireChance>	0.200000	</stateFireChance>
            <fallingOutModel>
            </fallingOutModel>
          </state>
        </states>
        <repairDestructedAfter>	-1.000000	</repairDestructedAfter>
        <fireMountPoint>
        </fireMountPoint>
        <componentTypeQuota>	1.000000	</componentTypeQuota>
        <componentPosition>Front</componentPosition>
      </upgrade>
    </part>
    <part>
      <name>center1</name>
      <partId>	3	</partId>
      <groupId>	3	</groupId>
      <mountPoint>ship1/HP_part1</mountPoint>
      <upgrade>
        <id>	1	</id>
        <bBoxes>
          <bbox>
            <position>	-14.805000 2.970000 -6.390000	</position>
            <size>	3.240000 3.330000 6.210000	</size>
            <armorFront>	0.000000 0.000000 0.000000	</armorFront>
            <armorBack>	0.000000 0.000000 0.000000	</armorBack>
            <absorption>	1.000000	</absorption>
            <rotation>	0.000000 0.000000 0.000000 1.000000	</rotation>
          </bbox>
          <bbox>
            <position>	-14.220000 4.995000 -6.030000	</position>
            <size>	1.530000 0.990000 1.170000	</size>
            <armorFront>	0.000000 0.000000 0.000000	</armorFront>
            <armorBack>	0.000000 0.000000 0.000000	</armorBack>
            <absorption>	1.000000	</absorption>
            <rotation>	0.000000 0.000000 0.000000 1.000000	</rotation>
          </bbox>
        </bBoxes>
        <health>	150	</health>
        <componentType>Collidable</componentType>
        <componentXml>server.todo.xml</componentXml>
        <states>
          <state>
            <id>	1	</id>
            <stateAction>	0	</stateAction>
            <stateHelthCfc>	1.000000	</stateHelthCfc>
            <model>content/dest/ship/US/Subchaser_destructible/Winter/mech_CV_Subchaser_part1.model</model>
            <stateAnimation>
            </stateAnimation>
            <subItems>
            </subItems>
            <animationController>
            </animationController>
            <stateFireChance>	0.200000	</stateFireChance>
            <fallingOutModel>
            </fallingOutModel>
          </state>
          <state>
            <id>	2	</id>
            <stateAction>	0	</stateAction>
            <stateHelthCfc>	0.800000	</stateHelthCfc>
            <model>content/dest/ship/US/Subchaser_destructible/Winter/mech_CV_Subchaser_part1.model</model>
            <stateAnimation>
            </stateAnimation>
            <subItems>
            </subItems>
            <animationController>
            </animationController>
            <stateFireChance>	0.200000	</stateFireChance>
            <fallingOutModel>
            </fallingOutModel>
          </state>
          <state>
            <id>	3	</id>
            <usage>
            </usage>
            <stateAction>	0	</stateAction>
            <stateHelthCfc>	0.300000	</stateHelthCfc>
            <model>content/dest/ship/US/Subchaser_destructible/Winter/mech_CV_Subchaser_part1.model</model>
            <stateAnimation>
            </stateAnimation>
            <subItems>
            </subItems>
            <animationController>
            </animationController>
            <stateFireChance>	0.200000	</stateFireChance>
            <fallingOutModel>
            </fallingOutModel>
          </state>
          <state>
            <id>	4	</id>
            <bBoxes>
              <bbox>
                <position>	0.174165 65.245610 -0.097847	</position>
                <size>0 0 0</size>
                <armorFront>0.0 0.0 0.0</armorFront>
                <armorBack>0.0 0.0 0.0</armorBack>
                <absorption>	1.000000	</absorption>
                <rotation>	0.000000 0.000000 0.000000 1.000000	</rotation>
              </bbox>
            </bBoxes>
            <usage>
            </usage>
            <stateAction>	0	</stateAction>
            <stateHelthCfc>	0.000000	</stateHelthCfc>
            <model>content/dest/ship/US/Subchaser_destructible/Winter/mech_CV_Subchaser_part1_crash.model</model>
            <effectOnStart>
              <effect>
                <name>EFFECT_w_part_exposion_small</name>
                <mountPoint>HP_explosion_part1</mountPoint>
              </effect>
            </effectOnStart>
            <effectState>
              <effect>
                <name>EFFECT_w_prop_black_smoke_small_02</name>
                <mountPoint>HP_explosion_part1</mountPoint>
              </effect>
            </effectState>
            <stateAnimation>death,idle</stateAnimation>
            <subItems>
            </subItems>
            <animationController>
            </animationController>
            <stateFireChance>	0.200000	</stateFireChance>
            <fallingOutModel>
            </fallingOutModel>
          </state>
          <state>
            <id>	5	</id>
            <bBoxes>
              <bbox>
                <position>	-14.805000 2.970000 -6.390000	</position>
                <size>2.268 2.331 4.347</size>
                <armorFront>0.0 0.0 0.0</armorFront>
                <armorBack>0.0 0.0 0.0</armorBack>
                <absorption>	1.000000	</absorption>
                <rotation>	0.000000 0.000000 0.000000 1.000000	</rotation>
              </bbox>
            </bBoxes>
            <usage>crash</usage>
            <stateAction>	0	</stateAction>
            <stateHelthCfc>0.00000</stateHelthCfc>
            <model>content/dest/ship/US/Fletcher_destructible/mechPC_61_Fletcher_destructible_Empty.model</model>
            <subItems>
            </subItems>
            <animationController>
            </animationController>
            <stateFireChance>	0.200000	</stateFireChance>
            <fallingOutModel>
            </fallingOutModel>
            <stateAnimation>
            </stateAnimation>
            <model>
            </model>
          </state>
        </states>
        <repairDestructedAfter>	-1.000000	</repairDestructedAfter>
        <fireMountPoint>HP_part1</fireMountPoint>
        <fire>
          <effectFire>EFFECT_fire_small</effectFire>
          <fire_chance>0.02</fire_chance>
          <extinguish_time>10.0</extinguish_time>
          <fire_damage>10%</fire_damage>
          <tickLength>	1	</tickLength>
          <extinguish_chance>
            <baseChance>0.05</baseChance>
            <vMin>	200	</vMin>
            <pMin>1.0</pMin>
            <vMax>	500	</vMax>
            <pMax>3.0</pMax>
          </extinguish_chance>
        </fire>
        <componentTypeQuota>	1.000000	</componentTypeQuota>
        <componentPosition>Front</componentPosition>
      </upgrade>
    </part>
    <part>
      <name>aa_gun1_1</name>
      <partId>	4	</partId>
      <groupId>	6	</groupId>
      <mountPoint>ship1/HP_antiaircraft_gun_03</mountPoint>
      <upgrade>
        <id>	1	</id>
        <bBoxes>
        </bBoxes>
        <health>	0	</health>
        <componentType>Collidable</componentType>
        <componentXml>scenarioturret</componentXml>
        <states>
          <state>
            <id>	1	</id>
            <stateHelthCfc>	1.000000	</stateHelthCfc>
            <usage>
            </usage>
            <stateAction>	0	</stateAction>
            <model>content/dest/ship/US/Subchaser_destructible/Winter/mech_CV_Subchaser_gun_2.model</model>
            <animationController>
            </animationController>
            <subItems>
            </subItems>
            <animationController>
            </animationController>
            <stateFireChance>	0.200000	</stateFireChance>
            <fallingOutModel>
            </fallingOutModel>
            <stateAnimation>
            </stateAnimation>
          </state>
          <state>
            <id>	2	</id>
            <stateHelthCfc>	0.000000	</stateHelthCfc>
            <usage>
            </usage>
            <stateAction>	0	</stateAction>
            <model>content/dest/ship/US/Subchaser_destructible/Winter/mech_CV_Subchaser_gun_2.model</model>
            <effectOnStart>
              <effect>
                <name>EFFECT_w_part_exposion_small</name>
                <mountPoint>HP_base</mountPoint>
              </effect>
            </effectOnStart>
            <effectState>
              <effect>
                <name>EFFECT_w_prop_black_smoke_small_02</name>
                <mountPoint>HP_base</mountPoint>
              </effect>
            </effectState>
            <animationController>
            </animationController>
            <subItems>
            </subItems>
            <animationController>
            </animationController>
            <stateFireChance>	0.200000	</stateFireChance>
            <fallingOutModel>
            </fallingOutModel>
            <stateAnimation>
            </stateAnimation>
          </state>
          <state>
            <id>	3	</id>
            <stateHelthCfc>0.00000</stateHelthCfc>
            <usage>crash</usage>
            <stateAction>	0	</stateAction>
            <model>content/dest/ship/US/Fletcher_destructible/mechPC_61_Fletcher_destructible_Empty.model</model>
            <subItems>
            </subItems>
            <animationController>
            </animationController>
            <stateFireChance>	0.200000	</stateFireChance>
            <fallingOutModel>
            </fallingOutModel>
            <stateAnimation>
            </stateAnimation>
            <model>
            </model>
          </state>
        </states>
        <repairDestructedAfter>	-1.000000	</repairDestructedAfter>
        <fireMountPoint>
        </fireMountPoint>
        <componentTypeQuota>	1.000000	</componentTypeQuota>
        <componentPosition>Front</componentPosition>
      </upgrade>
    </part>
    <part>
      <name>aa_gun1_2</name>
      <partId>	6	</partId>
      <groupId>	6	</groupId>
      <mountPoint>ship1/HP_antiaircraft_gun_02</mountPoint>
      <upgrade>
        <id>	1	</id>
        <bBoxes>
        </bBoxes>
        <health>	0	</health>
        <componentType>Collidable</componentType>
        <componentXml>scenarioturret</componentXml>
        <states>
          <state>
            <id>	1	</id>
            <stateHelthCfc>	1.000000	</stateHelthCfc>
            <usage>
            </usage>
            <stateAction>	0	</stateAction>
            <model>content/dest/ship/US/Subchaser_destructible/Winter/mech_CV_Subchaser_gun_2.model</model>
            <animationController>
            </animationController>
            <subItems>
            </subItems>
            <animationController>
            </animationController>
            <stateFireChance>	0.200000	</stateFireChance>
            <fallingOutModel>
            </fallingOutModel>
            <stateAnimation>
            </stateAnimation>
          </state>
          <state>
            <id>	2	</id>
            <stateHelthCfc>	0.000000	</stateHelthCfc>
            <usage>
            </usage>
            <stateAction>	0	</stateAction>
            <model>content/dest/ship/US/Subchaser_destructible/Winter/mech_CV_Subchaser_gun_2.model</model>
            <effectOnStart>
              <effect>
                <name>EFFECT_w_part_exposion_small</name>
                <mountPoint>HP_base</mountPoint>
              </effect>
            </effectOnStart>
            <effectState>
              <effect>
                <name>EFFECT_w_prop_black_smoke_small_02</name>
                <mountPoint>HP_base</mountPoint>
              </effect>
            </effectState>
            <animationController>
            </animationController>
            <subItems>
            </subItems>
            <animationController>
            </animationController>
            <stateFireChance>	0.200000	</stateFireChance>
            <fallingOutModel>
            </fallingOutModel>
            <stateAnimation>
            </stateAnimation>
          </state>
          <state>
            <id>	3	</id>
            <stateHelthCfc>0.00000</stateHelthCfc>
            <usage>crash</usage>
            <stateAction>	0	</stateAction>
            <model>content/dest/ship/US/Fletcher_destructible/mechPC_61_Fletcher_destructible_Empty.model</model>
            <subItems>
            </subItems>
            <animationController>
            </animationController>
            <stateFireChance>	0.200000	</stateFireChance>
            <fallingOutModel>
            </fallingOutModel>
            <stateAnimation>
            </stateAnimation>
            <model>
            </model>
          </state>
        </states>
        <repairDestructedAfter>	-1.000000	</repairDestructedAfter>
        <fireMountPoint>
        </fireMountPoint>
        <componentTypeQuota>	1.000000	</componentTypeQuota>
        <componentPosition>Front</componentPosition>
      </upgrade>
    </part>
    <part>
      <name>aa_gun1_3</name>
      <partId>	7	</partId>
      <groupId>	6	</groupId>
      <mountPoint>ship1/HP_antiaircraft_gun_01</mountPoint>
      <upgrade>
        <id>	1	</id>
        <bBoxes>
        </bBoxes>
        <health>	0	</health>
        <componentType>Collidable</componentType>
        <componentXml>scenarioturret</componentXml>
        <states>
          <state>
            <id>	1	</id>
            <stateHelthCfc>	1.000000	</stateHelthCfc>
            <usage>
            </usage>
            <stateAction>	0	</stateAction>
            <model>content/dest/ship/US/Subchaser_destructible/Winter/mech_CV_Subchaser_gun_2.model</model>
            <animationController>
            </animationController>
            <subItems>
            </subItems>
            <animationController>
            </animationController>
            <stateFireChance>	0.200000	</stateFireChance>
            <fallingOutModel>
            </fallingOutModel>
            <stateAnimation>
            </stateAnimation>
          </state>
          <state>
            <id>	2	</id>
            <stateHelthCfc>	0.000000	</stateHelthCfc>
            <usage>
            </usage>
            <stateAction>	0	</stateAction>
            <model>content/dest/ship/US/Subchaser_destructible/Winter/mech_CV_Subchaser_gun_2.model</model>
            <effectOnStart>
              <effect>
                <name>EFFECT_w_part_exposion_small</name>
                <mountPoint>HP_base</mountPoint>
              </effect>
            </effectOnStart>
            <effectState>
              <effect>
                <name>EFFECT_w_prop_black_smoke_small_02</name>
                <mountPoint>HP_base</mountPoint>
              </effect>
            </effectState>
            <animationController>
            </animationController>
            <subItems>
            </subItems>
            <animationController>
            </animationController>
            <stateFireChance>	0.200000	</stateFireChance>
            <fallingOutModel>
            </fallingOutModel>
            <stateAnimation>
            </stateAnimation>
          </state>
          <state>
            <id>	3	</id>
            <stateHelthCfc>0.00000</stateHelthCfc>
            <usage>crash</usage>
            <stateAction>	0	</stateAction>
            <model>content/dest/ship/US/Fletcher_destructible/mechPC_61_Fletcher_destructible_Empty.model</model>
            <subItems>
            </subItems>
            <animationController>
            </animationController>
            <stateFireChance>	0.200000	</stateFireChance>
            <fallingOutModel>
            </fallingOutModel>
            <stateAnimation>
            </stateAnimation>
            <model>
            </model>
          </state>
        </states>
        <repairDestructedAfter>	-1.000000	</repairDestructedAfter>
        <fireMountPoint>
        </fireMountPoint>
        <componentTypeQuota>	1.000000	</componentTypeQuota>
        <componentPosition>Front</componentPosition>
      </upgrade>
    </part>
    <part>
      <name>rocket1</name>
      <partId>	8	</partId>
      <groupId>	6	</groupId>
      <mountPoint>ship1/HP_rockets</mountPoint>
      <upgrade>
        <id>	1	</id>
        <bBoxes>
        </bBoxes>
        <health>	0	</health>
        <componentType>Collidable</componentType>
        <componentXml>scenarioTurret</componentXml>
        <states>
          <state>
            <id>	1	</id>
            <stateHelthCfc>1.00000</stateHelthCfc>
            <usage>
            </usage>
            <stateAction>	0	</stateAction>
            <model>content/dest/ship/US/Subchaser_destructible/Winter/mech_CV_Subchaser_rockets.model</model>
            <effectsTriggered>
              <effect>
                <trigger>SHOT1</trigger>
                <name>EFFECT_Katusha_Muzzle_Flash</name>
                <mountPoint>HP_main_fire1</mountPoint>
              </effect>
              <effect>
                <trigger>SHOT2</trigger>
                <name>EFFECT_Katusha_Muzzle_Flash</name>
                <mountPoint>HP_main_fire2</mountPoint>
              </effect>
              <effect>
                <trigger>SHOT3</trigger>
                <name>EFFECT_Katusha_Muzzle_Flash</name>
                <mountPoint>HP_main_fire3</mountPoint>
              </effect>
              <effect>
                <trigger>SHOT4</trigger>
                <name>EFFECT_Katusha_Muzzle_Flash</name>
                <mountPoint>HP_main_fire4</mountPoint>
              </effect>
              <effect>
                <trigger>SHOT5</trigger>
                <name>EFFECT_Katusha_Muzzle_Flash</name>
                <mountPoint>HP_main_fire5</mountPoint>
              </effect>
              <effect>
                <trigger>SHOT6</trigger>
                <name>EFFECT_Katusha_Muzzle_Flash</name>
                <mountPoint>HP_main_fire6</mountPoint>
              </effect>
              <effect>
                <trigger>SHOT7</trigger>
                <name>EFFECT_Katusha_Muzzle_Flash</name>
                <mountPoint>HP_main_fire7</mountPoint>
              </effect>
              <effect>
                <trigger>SHOT8</trigger>
                <name>EFFECT_Katusha_Muzzle_Flash</name>
                <mountPoint>HP_main_fire8</mountPoint>
              </effect>
            </effectsTriggered>
            <animationController>
            </animationController>
            <stateFireChance>	0.200000	</stateFireChance>
          </state>
          <state>
            <id>	2	</id>
            <stateHelthCfc>	0.000000	</stateHelthCfc>
            <usage>
            </usage>
            <stateAction>	0	</stateAction>
            <model>content/dest/ship/US/Subchaser_destructible/Winter/mech_CV_Subchaser_rockets.model</model>
            <effectOnStart>
              <effect>
                <name>EFFECT_w_part_exposion_small</name>
                <mountPoint>HP_main_rockets</mountPoint>
              </effect>
            </effectOnStart>
            <effectState>
              <effect>
                <name>EFFECT_w_prop_black_smoke_small_02</name>
                <mountPoint>HP_main_rockets</mountPoint>
              </effect>
            </effectState>
            <animationController>
            </animationController>
            <stateFireChance>	0.200000	</stateFireChance>
          </state>
          <state>
            <id>	3	</id>
            <stateHelthCfc>0.00000</stateHelthCfc>
            <usage>crash</usage>
            <stateAction>	0	</stateAction>
            <model>content/dest/ship/US/Fletcher_destructible/mechPC_61_Fletcher_destructible_Empty.model</model>
            <animationController>
            </animationController>
            <stateFireChance>	0.200000	</stateFireChance>
          </state>
        </states>
        <repairDestructedAfter>	-1.000000	</repairDestructedAfter>
        <fireMountPoint>
        </fireMountPoint>
        <componentTypeQuota>	1.000000	</componentTypeQuota>
        <componentPosition>Front</componentPosition>
      </upgrade>
    </part>
    <part>
      <name>	gun1	</name>
      <partId>	9	</partId>
      <groupId>	6	</groupId>
      <mountPoint>ship1/HP_gun_01</mountPoint>
      <upgrade>
        <id>	1	</id>
        <bBoxes>
        </bBoxes>
        <health>	0	</health>
        <componentType>Collidable</componentType>
        <componentXml>scenarioturret</componentXml>
        <states>
          <state>
            <id>	1	</id>
            <stateHelthCfc>	1.000000	</stateHelthCfc>
            <usage>
            </usage>
            <stateAction>	0	</stateAction>
            <model>content/dest/ship/US/Subchaser_destructible/Winter/mech_CV_Subchaser_gun_1.model</model>
            <subItems>
            </subItems>
            <animationController>
            </animationController>
            <stateFireChance>	0.200000	</stateFireChance>
            <fallingOutModel>
            </fallingOutModel>
            <stateAnimation>
            </stateAnimation>
          </state>
          <state>
            <id>	2	</id>
            <stateHelthCfc>	0.000000	</stateHelthCfc>
            <usage>
            </usage>
            <stateAction>	0	</stateAction>
            <model>content/dest/ship/US/Subchaser_destructible/Winter/mech_CV_Subchaser_gun_1.model</model>
            <effectOnStart>
              <effect>
                <name>EFFECT_w_part_exposion_small</name>
                <mountPoint>HP_base</mountPoint>
              </effect>
            </effectOnStart>
            <effectState>
              <effect>
                <name>EFFECT_w_prop_black_smoke_small_02</name>
                <mountPoint>HP_base</mountPoint>
              </effect>
            </effectState>
            <animationController>
            </animationController>
            <subItems>
            </subItems>
            <animationController>
            </animationController>
            <stateFireChance>	0.200000	</stateFireChance>
            <fallingOutModel>
            </fallingOutModel>
            <stateAnimation>
            </stateAnimation>
          </state>
          <state>
            <id>	3	</id>
            <stateHelthCfc>0.00000</stateHelthCfc>
            <usage>crash</usage>
            <stateAction>	0	</stateAction>
            <model>content/dest/ship/US/Fletcher_destructible/mechPC_61_Fletcher_destructible_Empty.model</model>
            <subItems>
            </subItems>
            <animationController>
            </animationController>
            <stateFireChance>	0.200000	</stateFireChance>
            <fallingOutModel>
            </fallingOutModel>
            <stateAnimation>
            </stateAnimation>
            <model>
            </model>
          </state>
        </states>
        <repairDestructedAfter>	-1.000000	</repairDestructedAfter>
        <fireMountPoint>
        </fireMountPoint>
        <componentTypeQuota>	1.000000	</componentTypeQuota>
        <componentPosition>Front</componentPosition>
      </upgrade>
    </part>
    <part>
      <name>ship2</name>
      <partId>	10	</partId>
      <groupId>	4	</groupId>
      <mountPoint>hull/HP_sp_5</mountPoint>
      <upgrade>
        <id>	1	</id>
        <bBoxes>
          <bbox>
            <position>	19.935000 0.675000 5.310000	</position>
            <size>	6.660000 4.050000 35.820000	</size>
            <armorFront>	0.000000 0.000000 0.000000	</armorFront>
            <armorBack>	0.000000 0.000000 0.000000	</armorBack>
            <absorption>	0.200000	</absorption>
            <rotation>	0.000000 0.000000 0.000000 1.000000	</rotation>
          </bbox>
        </bBoxes>
        <health>	450	</health>
        <componentType>Collidable</componentType>
        <componentXml>server.todo.xml</componentXml>
        <states>
          <state>
            <id>	1	</id>
            <usage>
            </usage>
            <stateAction>	0	</stateAction>
            <stateHelthCfc>	1.000000	</stateHelthCfc>
            <model>content/dest/ship/US/Subchaser_destructible/Winter/mech_CV_Subchaser.model</model>
            <effectState>
              <effect>
                <name>EFFECT_static_ship_39</name>
                <mountPoint>HP_stream</mountPoint>
              </effect>
            </effectState>
            <stateAnimation>
            </stateAnimation>
            <subItems>
            </subItems>
            <animationController>
            </animationController>
            <stateFireChance>	0.200000	</stateFireChance>
            <fallingOutModel>
            </fallingOutModel>
          </state>
          <state>
            <id>	2	</id>
            <usage>
            </usage>
            <stateAction>	0	</stateAction>
            <stateHelthCfc>	0.800000	</stateHelthCfc>
            <model>content/dest/ship/US/Subchaser_destructible/Winter/mech_CV_Subchaser.model</model>
            <effectState>
              <effect>
                <name>EFFECT_static_ship_39</name>
                <mountPoint>HP_stream</mountPoint>
              </effect>
            </effectState>
            <stateAnimation>
            </stateAnimation>
            <subItems>
            </subItems>
            <animationController>
            </animationController>
            <stateFireChance>	0.200000	</stateFireChance>
            <fallingOutModel>
            </fallingOutModel>
          </state>
          <state>
            <id>	3	</id>
            <usage>
            </usage>
            <stateAction>	0	</stateAction>
            <stateHelthCfc>	0.300000	</stateHelthCfc>
            <model>content/dest/ship/US/Subchaser_destructible/Winter/mech_CV_Subchaser.model</model>
            <effectState>
              <effect>
                <name>EFFECT_static_ship_39</name>
                <mountPoint>HP_stream</mountPoint>
              </effect>
            </effectState>
            <stateAnimation>
            </stateAnimation>
            <subItems>
            </subItems>
            <animationController>
            </animationController>
            <stateFireChance>	0.200000	</stateFireChance>
            <fallingOutModel>
            </fallingOutModel>
          </state>
          <state>
            <id>	4	</id>
            <bBoxes>
              <bbox>
                <position>	19.935000 0.675000 5.310000	</position>
                <size>4.662 2.835 25.074</size>
                <armorFront>0.0 0.0 0.0</armorFront>
                <armorBack>0.0 0.0 0.0</armorBack>
                <absorption>	1.000000	</absorption>
                <rotation>	0.000000 0.000000 0.000000 1.000000	</rotation>
              </bbox>
            </bBoxes>
            <usage>crash</usage>
            <stateAction>	0	</stateAction>
            <stateHelthCfc>	0.000000	</stateHelthCfc>
            <model>content/dest/ship/US/Subchaser_destructible/Winter/mech_CV_Subchaser_crash.model</model>
            <effectState>
            </effectState>
            <effectOnStart>
              <effect>
                <name>EFFECT_w_part_exposion_small</name>
                <mountPoint>HP_explosion_part1</mountPoint>
              </effect>
              <effect>
                <name>EFFECT_w_part_exposion_small</name>
                <mountPoint>HP_explosion_gun_nose</mountPoint>
              </effect>
              <effect>
                <name>EFFECT_w_part_exposion_small</name>
                <mountPoint>HP_explosion_gun_end</mountPoint>
              </effect>
            </effectOnStart>
            <stateAnimation>death,idle</stateAnimation>
            <affectedParts>
              <part>
                <partID>	11	</partID>
                <minimalPartState>	5	</minimalPartState>
              </part>
              <part>
                <partID>	12	</partID>
                <minimalPartState>	3	</minimalPartState>
              </part>
              <part>
                <partID>	13	</partID>
                <minimalPartState>	3	</minimalPartState>
              </part>
              <part>
                <partID>	14	</partID>
                <minimalPartState>	3	</minimalPartState>
              </part>
              <part>
                <partID>	15	</partID>
                <minimalPartState>	3	</minimalPartState>
              </part>
              <part>
                <partID>	16	</partID>
                <minimalPartState>	3	</minimalPartState>
              </part>
            </affectedParts>
            <subItems>
            </subItems>
            <animationController>
            </animationController>
            <stateFireChance>	0.200000	</stateFireChance>
            <fallingOutModel>
            </fallingOutModel>
          </state>
        </states>
        <repairDestructedAfter>	-1.000000	</repairDestructedAfter>
        <fireMountPoint>
        </fireMountPoint>
        <componentTypeQuota>	1.000000	</componentTypeQuota>
        <componentPosition>Front</componentPosition>
      </upgrade>
    </part>
    <part>
      <name>center2</name>
      <partId>	11	</partId>
      <groupId>	5	</groupId>
      <mountPoint>ship2/HP_part1</mountPoint>
      <upgrade>
        <id>	1	</id>
        <bBoxes>
          <bbox>
            <position>	19.800000 3.060000 7.470000	</position>
            <size>	3.240000 3.060000 5.400000	</size>
            <armorFront>	0.000000 0.000000 0.000000	</armorFront>
            <armorBack>	0.000000 0.000000 0.000000	</armorBack>
            <absorption>	1.000000	</absorption>
            <rotation>	0.000000 0.000000 0.000000 1.000000	</rotation>
          </bbox>
          <bbox>
            <position>	20.340000 4.950000 8.910000	</position>
            <size>	1.530000 0.990000 1.170000	</size>
            <armorFront>	0.000000 0.000000 0.000000	</armorFront>
            <armorBack>	0.000000 0.000000 0.000000	</armorBack>
            <absorption>	1.000000	</absorption>
            <rotation>	0.000000 0.000000 0.000000 1.000000	</rotation>
          </bbox>
        </bBoxes>
        <health>	150	</health>
        <componentType>Collidable</componentType>
        <componentXml>server.todo.xml</componentXml>
        <states>
          <state>
            <id>	1	</id>
            <usage>
            </usage>
            <stateAction>	0	</stateAction>
            <stateHelthCfc>	1.000000	</stateHelthCfc>
            <model>content/dest/ship/US/Subchaser_destructible/Winter/mech_CV_Subchaser_part1.model</model>
            <stateAnimation>
            </stateAnimation>
            <subItems>
            </subItems>
            <animationController>
            </animationController>
            <stateFireChance>	0.200000	</stateFireChance>
            <fallingOutModel>
            </fallingOutModel>
          </state>
          <state>
            <id>	2	</id>
            <usage>
            </usage>
            <stateAction>	0	</stateAction>
            <stateHelthCfc>	0.800000	</stateHelthCfc>
            <model>content/dest/ship/US/Subchaser_destructible/Winter/mech_CV_Subchaser_part1.model</model>
            <stateAnimation>
            </stateAnimation>
            <subItems>
            </subItems>
            <animationController>
            </animationController>
            <stateFireChance>	0.200000	</stateFireChance>
            <fallingOutModel>
            </fallingOutModel>
          </state>
          <state>
            <id>	3	</id>
            <usage>
            </usage>
            <stateAction>	0	</stateAction>
            <stateHelthCfc>	0.300000	</stateHelthCfc>
            <model>content/dest/ship/US/Subchaser_destructible/Winter/mech_CV_Subchaser_part1.model</model>
            <stateAnimation>
            </stateAnimation>
            <subItems>
            </subItems>
            <animationController>
            </animationController>
            <stateFireChance>	0.200000	</stateFireChance>
            <fallingOutModel>
            </fallingOutModel>
          </state>
          <state>
            <id>	4	</id>
            <bBoxes>
              <bbox>
                <position>	0.174165 65.245610 -0.097847	</position>
                <size>0 0 0</size>
                <armorFront>0.0 0.0 0.0</armorFront>
                <armorBack>0.0 0.0 0.0</armorBack>
                <absorption>	1.000000	</absorption>
                <rotation>	0.000000 0.000000 0.000000 1.000000	</rotation>
              </bbox>
            </bBoxes>
            <usage>
            </usage>
            <stateAction>	0	</stateAction>
            <stateHelthCfc>	0.000000	</stateHelthCfc>
            <model>content/dest/ship/US/Subchaser_destructible/Winter/mech_CV_Subchaser_part1_crash.model</model>
            <effectOnStart>
              <effect>
                <name>EFFECT_w_part_exposion_small</name>
                <mountPoint>HP_explosion_part1</mountPoint>
              </effect>
            </effectOnStart>
            <effectState>
              <effect>
                <name>EFFECT_w_prop_black_smoke_small_02</name>
                <mountPoint>HP_explosion_part1</mountPoint>
              </effect>
            </effectState>
            <stateAnimation>death,idle</stateAnimation>
            <subItems>
            </subItems>
            <animationController>
            </animationController>
            <stateFireChance>	0.200000	</stateFireChance>
            <fallingOutModel>
            </fallingOutModel>
          </state>
          <state>
            <id>	5	</id>
            <bBoxes>
              <bbox>
                <position>	19.800000 3.060000 7.470000	</position>
                <size>2.268 2.142 3.78</size>
                <armorFront>0.0 0.0 0.0</armorFront>
                <armorBack>0.0 0.0 0.0</armorBack>
                <absorption>	1.000000	</absorption>
                <rotation>	0.000000 0.000000 0.000000 1.000000	</rotation>
              </bbox>
            </bBoxes>
            <stateAction>	0	</stateAction>
            <stateHelthCfc>0.00000</stateHelthCfc>
            <usage>crash</usage>
            <model>content/dest/ship/US/Fletcher_destructible/mechPC_61_Fletcher_destructible_Empty.model</model>
            <subItems>
            </subItems>
            <animationController>
            </animationController>
            <stateFireChance>	0.200000	</stateFireChance>
            <fallingOutModel>
            </fallingOutModel>
            <stateAnimation>
            </stateAnimation>
            <model>
            </model>
          </state>
        </states>
        <repairDestructedAfter>	-1.000000	</repairDestructedAfter>
        <fireMountPoint>HP_part1</fireMountPoint>
        <fire>
          <effectFire>EFFECT_fire_small</effectFire>
          <fire_chance>0.02</fire_chance>
          <extinguish_time>10.0</extinguish_time>
          <fire_damage>10%</fire_damage>
          <tickLength>	1	</tickLength>
          <extinguish_chance>
            <baseChance>0.05</baseChance>
            <vMin>	200	</vMin>
            <pMin>1.0</pMin>
            <vMax>	500	</vMax>
            <pMax>3.0</pMax>
          </extinguish_chance>
        </fire>
        <componentTypeQuota>	1.000000	</componentTypeQuota>
        <componentPosition>Front</componentPosition>
      </upgrade>
    </part>
    <part>
      <name>aa_gun2_1</name>
      <partId>	12	</partId>
      <groupId>	6	</groupId>
      <mountPoint>ship2/HP_antiaircraft_gun_03</mountPoint>
      <upgrade>
        <id>	1	</id>
        <bBoxes>
        </bBoxes>
        <health>	0	</health>
        <componentType>Collidable</componentType>
        <componentXml>scenarioturret</componentXml>
        <states>
          <state>
            <id>	1	</id>
            <stateHelthCfc>	1.000000	</stateHelthCfc>
            <usage>
            </usage>
            <stateAction>	0	</stateAction>
            <model>content/dest/ship/US/Subchaser_destructible/Winter/mech_CV_Subchaser_gun_2.model</model>
            <animationController>
            </animationController>
            <subItems>
            </subItems>
            <animationController>
            </animationController>
            <stateFireChance>	0.200000	</stateFireChance>
            <fallingOutModel>
            </fallingOutModel>
            <stateAnimation>
            </stateAnimation>
          </state>
          <state>
            <id>	2	</id>
            <stateHelthCfc>	0.000000	</stateHelthCfc>
            <usage>
            </usage>
            <stateAction>	0	</stateAction>
            <model>content/dest/ship/US/Subchaser_destructible/Winter/mech_CV_Subchaser_gun_2.model</model>
            <effectOnStart>
              <effect>
                <name>EFFECT_w_part_exposion_small</name>
                <mountPoint>HP_base</mountPoint>
              </effect>
            </effectOnStart>
            <effectState>
              <effect>
                <name>EFFECT_w_prop_black_smoke_small_02</name>
                <mountPoint>HP_base</mountPoint>
              </effect>
            </effectState>
            <animationController>
            </animationController>
            <subItems>
            </subItems>
            <animationController>
            </animationController>
            <stateFireChance>	0.200000	</stateFireChance>
            <fallingOutModel>
            </fallingOutModel>
            <stateAnimation>
            </stateAnimation>
          </state>
          <state>
            <id>	3	</id>
            <stateHelthCfc>0.00000</stateHelthCfc>
            <usage>crash</usage>
            <stateAction>	0	</stateAction>
            <model>content/dest/ship/US/Fletcher_destructible/mechPC_61_Fletcher_destructible_Empty.model</model>
            <subItems>
            </subItems>
            <animationController>
            </animationController>
            <stateFireChance>	0.200000	</stateFireChance>
            <fallingOutModel>
            </fallingOutModel>
            <stateAnimation>
            </stateAnimation>
            <model>
            </model>
          </state>
        </states>
        <repairDestructedAfter>	-1.000000	</repairDestructedAfter>
        <fireMountPoint>
        </fireMountPoint>
        <componentTypeQuota>	1.000000	</componentTypeQuota>
        <componentPosition>Front</componentPosition>
      </upgrade>
    </part>
    <part>
      <name>aa_gun2_2</name>
      <partId>	13	</partId>
      <groupId>	6	</groupId>
      <mountPoint>ship2/HP_antiaircraft_gun_02</mountPoint>
      <upgrade>
        <id>	1	</id>
        <bBoxes>
        </bBoxes>
        <health>	0	</health>
        <componentType>Collidable</componentType>
        <componentXml>scenarioturret</componentXml>
        <states>
          <state>
            <id>	1	</id>
            <stateHelthCfc>	1.000000	</stateHelthCfc>
            <usage>
            </usage>
            <stateAction>	0	</stateAction>
            <model>content/dest/ship/US/Subchaser_destructible/Winter/mech_CV_Subchaser_gun_2.model</model>
            <animationController>
            </animationController>
            <subItems>
            </subItems>
            <animationController>
            </animationController>
            <stateFireChance>	0.200000	</stateFireChance>
            <fallingOutModel>
            </fallingOutModel>
            <stateAnimation>
            </stateAnimation>
          </state>
          <state>
            <id>	2	</id>
            <stateHelthCfc>	0.000000	</stateHelthCfc>
            <usage>
            </usage>
            <stateAction>	0	</stateAction>
            <model>content/dest/ship/US/Subchaser_destructible/Winter/mech_CV_Subchaser_gun_2.model</model>
            <effectOnStart>
              <effect>
                <name>EFFECT_w_part_exposion_small</name>
                <mountPoint>HP_base</mountPoint>
              </effect>
            </effectOnStart>
            <effectState>
              <effect>
                <name>EFFECT_w_prop_black_smoke_small_02</name>
                <mountPoint>HP_base</mountPoint>
              </effect>
            </effectState>
            <animationController>
            </animationController>
            <subItems>
            </subItems>
            <animationController>
            </animationController>
            <stateFireChance>	0.200000	</stateFireChance>
            <fallingOutModel>
            </fallingOutModel>
            <stateAnimation>
            </stateAnimation>
          </state>
          <state>
            <id>	3	</id>
            <stateHelthCfc>0.00000</stateHelthCfc>
            <usage>crash</usage>
            <stateAction>	0	</stateAction>
            <model>content/dest/ship/US/Fletcher_destructible/mechPC_61_Fletcher_destructible_Empty.model</model>
            <subItems>
            </subItems>
            <animationController>
            </animationController>
            <stateFireChance>	0.200000	</stateFireChance>
            <fallingOutModel>
            </fallingOutModel>
            <stateAnimation>
            </stateAnimation>
            <model>
            </model>
          </state>
        </states>
        <repairDestructedAfter>	-1.000000	</repairDestructedAfter>
        <fireMountPoint>
        </fireMountPoint>
        <componentTypeQuota>	1.000000	</componentTypeQuota>
        <componentPosition>Front</componentPosition>
      </upgrade>
    </part>
    <part>
      <name>aa_gun2_3</name>
      <partId>	14	</partId>
      <groupId>	6	</groupId>
      <mountPoint>ship2/HP_antiaircraft_gun_01</mountPoint>
      <upgrade>
        <id>	1	</id>
        <bBoxes>
        </bBoxes>
        <health>	0	</health>
        <componentType>Collidable</componentType>
        <componentXml>scenarioturret</componentXml>
        <states>
          <state>
            <id>	1	</id>
            <stateHelthCfc>	1.000000	</stateHelthCfc>
            <usage>
            </usage>
            <stateAction>	0	</stateAction>
            <model>content/dest/ship/US/Subchaser_destructible/Winter/mech_CV_Subchaser_gun_2.model</model>
            <animationController>
            </animationController>
            <subItems>
            </subItems>
            <animationController>
            </animationController>
            <stateFireChance>	0.200000	</stateFireChance>
            <fallingOutModel>
            </fallingOutModel>
            <stateAnimation>
            </stateAnimation>
          </state>
          <state>
            <id>	2	</id>
            <stateHelthCfc>	0.000000	</stateHelthCfc>
            <usage>
            </usage>
            <stateAction>	0	</stateAction>
            <model>content/dest/ship/US/Subchaser_destructible/Winter/mech_CV_Subchaser_gun_2.model</model>
            <effectOnStart>
              <effect>
                <name>EFFECT_w_part_exposion_small</name>
                <mountPoint>HP_base</mountPoint>
              </effect>
            </effectOnStart>
            <effectState>
              <effect>
                <name>EFFECT_w_prop_black_smoke_small_02</name>
                <mountPoint>HP_base</mountPoint>
              </effect>
            </effectState>
            <animationController>
            </animationController>
            <subItems>
            </subItems>
            <animationController>
            </animationController>
            <stateFireChance>	0.200000	</stateFireChance>
            <fallingOutModel>
            </fallingOutModel>
            <stateAnimation>
            </stateAnimation>
          </state>
          <state>
            <id>	3	</id>
            <stateHelthCfc>0.00000</stateHelthCfc>
            <usage>crash</usage>
            <stateAction>	0	</stateAction>
            <model>content/dest/ship/US/Fletcher_destructible/mechPC_61_Fletcher_destructible_Empty.model</model>
            <subItems>
            </subItems>
            <animationController>
            </animationController>
            <stateFireChance>	0.200000	</stateFireChance>
            <fallingOutModel>
            </fallingOutModel>
            <stateAnimation>
            </stateAnimation>
            <model>
            </model>
          </state>
        </states>
        <repairDestructedAfter>	-1.000000	</repairDestructedAfter>
        <fireMountPoint>
        </fireMountPoint>
        <componentTypeQuota>	1.000000	</componentTypeQuota>
        <componentPosition>Front</componentPosition>
      </upgrade>
    </part>
    <part>
      <name>rocket2</name>
      <partId>	15	</partId>
      <groupId>	6	</groupId>
      <mountPoint>ship2/HP_rockets</mountPoint>
      <upgrade>
        <id>	1	</id>
        <bBoxes>
        </bBoxes>
        <health>	0	</health>
        <componentType>Collidable</componentType>
        <componentXml>scenarioTurret</componentXml>
        <states>
          <state>
            <id>	1	</id>
            <stateHelthCfc>1.00000</stateHelthCfc>
            <usage>
            </usage>
            <stateAction>	0	</stateAction>
            <model>content/dest/ship/US/Subchaser_destructible/Winter/mech_CV_Subchaser_rockets.model</model>
            <effectsTriggered>
              <effect>
                <trigger>SHOT9</trigger>
                <name>EFFECT_Katusha_Muzzle_Flash</name>
                <mountPoint>HP_main_fire1</mountPoint>
              </effect>
              <effect>
                <trigger>SHOT10</trigger>
                <name>EFFECT_Katusha_Muzzle_Flash</name>
                <mountPoint>HP_main_fire2</mountPoint>
              </effect>
              <effect>
                <trigger>SHOT11</trigger>
                <name>EFFECT_Katusha_Muzzle_Flash</name>
                <mountPoint>HP_main_fire3</mountPoint>
              </effect>
              <effect>
                <trigger>SHOT12</trigger>
                <name>EFFECT_Katusha_Muzzle_Flash</name>
                <mountPoint>HP_main_fire4</mountPoint>
              </effect>
              <effect>
                <trigger>SHOT13</trigger>
                <name>EFFECT_Katusha_Muzzle_Flash</name>
                <mountPoint>HP_main_fire5</mountPoint>
              </effect>
              <effect>
                <trigger>SHOT14</trigger>
                <name>EFFECT_Katusha_Muzzle_Flash</name>
                <mountPoint>HP_main_fire6</mountPoint>
              </effect>
              <effect>
                <trigger>SHOT15</trigger>
                <name>EFFECT_Katusha_Muzzle_Flash</name>
                <mountPoint>HP_main_fire7</mountPoint>
              </effect>
              <effect>
                <trigger>SHOT16</trigger>
                <name>EFFECT_Katusha_Muzzle_Flash</name>
                <mountPoint>HP_main_fire8</mountPoint>
              </effect>
            </effectsTriggered>
            <animationController>
            </animationController>
            <stateFireChance>	0.200000	</stateFireChance>
          </state>
          <state>
            <id>	2	</id>
            <stateHelthCfc>	0.000000	</stateHelthCfc>
            <usage>
            </usage>
            <stateAction>	0	</stateAction>
            <model>content/dest/ship/US/Subchaser_destructible/Winter/mech_CV_Subchaser_rockets.model</model>
            <effectOnStart>
              <effect>
                <name>EFFECT_w_part_exposion_small</name>
                <mountPoint>HP_main_rockets</mountPoint>
              </effect>
            </effectOnStart>
            <effectState>
              <effect>
                <name>EFFECT_w_prop_black_smoke_small_02</name>
                <mountPoint>HP_main_rockets</mountPoint>
              </effect>
            </effectState>
            <animationController>
            </animationController>
            <stateFireChance>	0.200000	</stateFireChance>
          </state>
          <state>
            <id>	3	</id>
            <stateHelthCfc>0.00000</stateHelthCfc>
            <usage>crash</usage>
            <stateAction>	0	</stateAction>
            <model>content/dest/ship/US/Fletcher_destructible/mechPC_61_Fletcher_destructible_Empty.model</model>
            <animationController>
            </animationController>
            <stateFireChance>	0.200000	</stateFireChance>
          </state>
        </states>
        <repairDestructedAfter>	-1.000000	</repairDestructedAfter>
        <fireMountPoint>
        </fireMountPoint>
        <componentTypeQuota>	1.000000	</componentTypeQuota>
        <componentPosition>Front</componentPosition>
      </upgrade>
    </part>
    <part>
      <name>	gun2	</name>
      <partId>	16	</partId>
      <groupId>	6	</groupId>
      <mountPoint>ship2/HP_gun_01</mountPoint>
      <upgrade>
        <id>	1	</id>
        <bBoxes>
        </bBoxes>
        <health>	0	</health>
        <componentType>Collidable</componentType>
        <componentXml>scenarioturret</componentXml>
        <states>
          <state>
            <id>	1	</id>
            <stateHelthCfc>	1.000000	</stateHelthCfc>
            <usage>
            </usage>
            <stateAction>	0	</stateAction>
            <model>content/dest/ship/US/Subchaser_destructible/Winter/mech_CV_Subchaser_gun_1.model</model>
            <subItems>
            </subItems>
            <animationController>
            </animationController>
            <stateFireChance>	0.200000	</stateFireChance>
            <fallingOutModel>
            </fallingOutModel>
            <stateAnimation>
            </stateAnimation>
          </state>
          <state>
            <id>	2	</id>
            <stateHelthCfc>	0.000000	</stateHelthCfc>
            <usage>
            </usage>
            <stateAction>	0	</stateAction>
            <model>content/dest/ship/US/Subchaser_destructible/Winter/mech_CV_Subchaser_gun_1.model</model>
            <effectOnStart>
              <effect>
                <name>EFFECT_w_part_exposion_small</name>
                <mountPoint>HP_base</mountPoint>
              </effect>
            </effectOnStart>
            <effectState>
              <effect>
                <name>EFFECT_w_prop_black_smoke_small_02</name>
                <mountPoint>HP_base</mountPoint>
              </effect>
            </effectState>
            <animationController>
            </animationController>
            <subItems>
            </subItems>
            <animationController>
            </animationController>
            <stateFireChance>	0.200000	</stateFireChance>
            <fallingOutModel>
            </fallingOutModel>
            <stateAnimation>
            </stateAnimation>
          </state>
          <state>
            <id>	3	</id>
            <stateHelthCfc>0.00000</stateHelthCfc>
            <usage>crash</usage>
            <stateAction>	0	</stateAction>
            <model>content/dest/ship/US/Fletcher_destructible/mechPC_61_Fletcher_destructible_Empty.model</model>
            <subItems>
            </subItems>
            <animationController>
            </animationController>
            <stateFireChance>	0.200000	</stateFireChance>
            <fallingOutModel>
            </fallingOutModel>
            <stateAnimation>
            </stateAnimation>
            <model>
            </model>
          </state>
        </states>
        <repairDestructedAfter>	-1.000000	</repairDestructedAfter>
        <fireMountPoint>
        </fireMountPoint>
        <componentTypeQuota>	1.000000	</componentTypeQuota>
        <componentPosition>Front</componentPosition>
      </upgrade>
    </part>
  </parts>
  <modelScaling>0.22</modelScaling>
</dest_subchaser_anim_winter_2_no_aa.xml>